{
  "cookies": [
    {
      "name": "ci_session",
      "value": "9e65i78s901l47eujbmuhtugfh5s86od",
      "domain": "effi.com.co",
      "path": "/",
      "expires": 1773472934.092239,
      "httpOnly": true,
      "secure": false,
      "sameSite": "Lax"
    }
  ],
  "origins": [
    {
      "origin": "https://effi.com.co",
      "localStorage": [
        {
          "name": "NRBA_SESSION",
          "value": "{\"value\":\"330458a9f5ac1983\",\"inactiveAt\":1773438732939,\"expiresAt\":1773451332939,\"updatedAt\":1773436933628,\"sessionReplayMode\":0,\"sessionReplaySentFirstChunk\":false,\"sessionTraceMode\":0,\"traceHarvestStarted\":false,\"loggingMode\":0,\"logApiMode\":0,\"serverTimeDiff\":2,\"custom\":{},\"numOfResets\":0,\"consent\":false}"
        },
        {
          "name": "pusherTransportTLS",
          "value": "{\"timestamp\":1773436934161,\"transport\":\"ws\",\"latency\":312}"
        }
      ]
    },
    {
      "origin": "https://www.google.com",
      "localStorage": [
        {
          "name": "rc::a",
          "value": "MWg4Y3RjOXIxeXp2Zg=="
        }
      ]
    }
  ]
}